pimask/__init__.py
pimask/annotator.py
pimask/cli.py
pimask-0.7.dist-info/LICENSE
pimask-0.7.dist-info/METADATA
pimask-0.7.dist-info/WHEEL
pimask-0.7.dist-info/entry_points.txt
pimask-0.7.dist-info/top_level.txt
pimask-0.7.dist-info/RECORD
